lisa_api-0.5.data/scripts/lisa-api-cli
lisa_api/__init__.py
lisa_api/frontend/urls.py
lisa_api/frontend/__init__.py
lisa_api/frontend/views.py
lisa_api/frontend/context_processors.py
lisa_api/frontend/templates/dashboard.html
lisa_api/frontend/templates/login.html
lisa_api/frontend/templates/changelog.html
lisa_api/frontend/templates/base.html
lisa_api/frontend/templates/plugins.html
lisa_api/frontend/templates/macros/username.html
lisa_api/frontend/migrations/__init__.py
lisa_api/frontend/templatetags/__init__.py
lisa_api/frontend/templatetags/active.py
lisa_api/frontend/templatetags/gravatar.py
lisa_api/frontend/static/img/anonymous.png
lisa_api/frontend/static/img/ajax-loader.gif
lisa_api/frontend/static/less/sidebar-mini.less
lisa_api/frontend/static/less/miscellaneous.less
lisa_api/frontend/static/less/bootstrap-social.less
lisa_api/frontend/static/less/core.less
lisa_api/frontend/static/less/mailbox.less
lisa_api/frontend/static/less/users-list.less
lisa_api/frontend/static/less/mixins.less
lisa_api/frontend/static/less/forms.less
lisa_api/frontend/static/less/variables.less
lisa_api/frontend/static/less/buttons.less
lisa_api/frontend/static/less/control-sidebar.less
lisa_api/frontend/static/less/dropdown.less
lisa_api/frontend/static/less/products.less
lisa_api/frontend/static/less/callout.less
lisa_api/frontend/static/less/alerts.less
lisa_api/frontend/static/less/invoice.less
lisa_api/frontend/static/less/info-box.less
lisa_api/frontend/static/less/404_500_errors.less
lisa_api/frontend/static/less/print.less
lisa_api/frontend/static/less/carousel.less
lisa_api/frontend/static/less/modal.less
lisa_api/frontend/static/less/sidebar.less
lisa_api/frontend/static/less/labels.less
lisa_api/frontend/static/less/AdminLTE.less
lisa_api/frontend/static/less/lockscreen.less
lisa_api/frontend/static/less/boxes.less
lisa_api/frontend/static/less/timeline.less
lisa_api/frontend/static/less/progress-bars.less
lisa_api-0.5.dist-info/RECORD
lisa_api-0.5.dist-info/metadata.json
lisa_api-0.5.dist-info/DESCRIPTION.rst
lisa_api-0.5.dist-info/METADATA
lisa_api-0.5.dist-info/entry_points.txt
lisa_api-0.5.dist-info/WHEEL
lisa_api-0.5.dist-info/pbr.json
lisa_api-0.5.dist-info/top_level.txt
