Metadata-Version: 2.0
Name: lisa-api
Version: 0.5
Summary: LISA Project API
Home-page: http://www.lisa-project.net
Author: Julien Syx
Author-email: julien@lisa-project.net
License: Apache
Platform: UNKNOWN
Classifier: Environment :: Console
Classifier: Intended Audience :: Information Technology
Classifier: Intended Audience :: System Administrators
Classifier: License :: OSI Approved :: Apache Software License
Classifier: Operating System :: POSIX :: Linux
Classifier: Programming Language :: Python
Classifier: Programming Language :: Python :: 2
Classifier: Programming Language :: Python :: 2.7
Classifier: Programming Language :: Python :: 3
Classifier: Programming Language :: Python :: 3.3
Classifier: Programming Language :: Python :: 3.4
Requires-Dist: pip (==1.5.6)
Requires-Dist: djangorestframework
Requires-Dist: django (>=1.8)
Requires-Dist: mysqlclient
Requires-Dist: django-rest-swagger
Requires-Dist: stevedore
Requires-Dist: colorlog
Requires-Dist: six
Requires-Dist: kombu
Requires-Dist: requests
Requires-Dist: cookiecutter
Requires-Dist: mistune
Requires-Dist: django-compressor
Requires-Dist: django-libsass
